{
  "generated_at": "2026-06-10T20:47:53.948757",
  "parameters": {
    "radius_km": 25.0,
    "fuel_type": "e5",
    "date_from": "2026-06-01",
    "date_to": "2026-07-01",
    "month": "2026-06",
    "window_label": "2026-06"
  },
  "stats": {
    "station_count": 17807,
    "price_record_count": 30001405,
    "brent_price_count": 168,
    "ingestion_count": 210,
    "price_date_from": "2026-02-24 23:00:03",
    "price_date_to": "2026-06-09 21:57:55",
    "recent_ingestions": [
      {
        "file_path": "prices/2026-06-09",
        "ingested_at": "2026-06-10 20:47:09.721225",
        "row_count": 244710
      },
      {
        "file_path": "stations/2026-06-09",
        "ingested_at": "2026-06-10 20:46:50.679273",
        "row_count": 17807
      },
      {
        "file_path": "prices/2026-06-08",
        "ingested_at": "2026-06-09 20:22:00.981462",
        "row_count": 2431857
      },
      {
        "file_path": "stations/2026-06-08",
        "ingested_at": "2026-06-09 20:21:20.612421",
        "row_count": 17805
      },
      {
        "file_path": "prices/2026-06-07",
        "ingested_at": "2026-06-08 20:36:27.533644",
        "row_count": 204413
      },
      {
        "file_path": "stations/2026-06-07",
        "ingested_at": "2026-06-08 20:36:07.198793",
        "row_count": 17805
      },
      {
        "file_path": "prices/2026-06-06",
        "ingested_at": "2026-06-07 19:48:47.410415",
        "row_count": 219879
      },
      {
        "file_path": "stations/2026-06-06",
        "ingested_at": "2026-06-07 19:48:27.411761",
        "row_count": 17805
      },
      {
        "file_path": "prices/2026-06-05",
        "ingested_at": "2026-06-06 19:48:50.029266",
        "row_count": 241747
      },
      {
        "file_path": "stations/2026-06-05",
        "ingested_at": "2026-06-06 19:48:32.080754",
        "row_count": 17804
      }
    ]
  },
  "regions": {
    "Hannover": {
      "lat": 52.37,
      "lng": 9.73,
      "leader_follower": [
        {
          "leader_brand": "ARAL",
          "follower_brand": "JET",
          "median_lag_minutes": 1.525,
          "event_count": 8
        },
        {
          "leader_brand": "ARAL",
          "follower_brand": "ESSO",
          "median_lag_minutes": 2.033333333333333,
          "event_count": 9
        },
        {
          "leader_brand": "ARAL",
          "follower_brand": "TotalEnergies",
          "median_lag_minutes": 4.05,
          "event_count": 9
        },
        {
          "leader_brand": "ARAL",
          "follower_brand": "TOTAL",
          "median_lag_minutes": 1438.1,
          "event_count": 8
        },
        {
          "leader_brand": "Shell",
          "follower_brand": "JET",
          "median_lag_minutes": 2.0166666666666666,
          "event_count": 7
        },
        {
          "leader_brand": "Shell",
          "follower_brand": "ESSO",
          "median_lag_minutes": 2.033333333333333,
          "event_count": 9
        },
        {
          "leader_brand": "Shell",
          "follower_brand": "TotalEnergies",
          "median_lag_minutes": 4.05,
          "event_count": 9
        },
        {
          "leader_brand": "Shell",
          "follower_brand": "TOTAL",
          "median_lag_minutes": 1437.7833333333333,
          "event_count": 8
        }
      ],
      "rockets_feathers": [
        {
          "brand": "ARAL",
          "avg_increase_cents": 18.766666666666666,
          "avg_decrease_cents": 0.7912144702842375,
          "avg_increase_speed_min": 316.81847222181966,
          "avg_decrease_speed_min": 43.39091300604982,
          "asymmetry_ratio": 0.13695827993157478
        },
        {
          "brand": "ESSO",
          "avg_increase_cents": 19.73469387755102,
          "avg_decrease_cents": 0.6753554502369666,
          "avg_increase_speed_min": 201.7258503404731,
          "avg_decrease_speed_min": 38.676393590598906,
          "asymmetry_ratio": 0.19172750307073114
        },
        {
          "brand": "JET",
          "avg_increase_cents": 18.870370370370374,
          "avg_decrease_cents": 0.6489821098087599,
          "avg_increase_speed_min": 124.7459876538013,
          "avg_decrease_speed_min": 41.26366440470823,
          "asymmetry_ratio": 0.33078149590850453
        },
        {
          "brand": "Shell",
          "avg_increase_cents": 19.462184873949578,
          "avg_decrease_cents": 0.6739869651459335,
          "avg_increase_speed_min": 216.41596638628852,
          "avg_decrease_speed_min": 39.084270803825746,
          "asymmetry_ratio": 0.18059790807699858
        },
        {
          "brand": "TOTAL",
          "avg_increase_cents": 14.222222222222221,
          "avg_decrease_cents": 0.4378283712784586,
          "avg_increase_speed_min": 284.54166666625275,
          "avg_decrease_speed_min": 35.40884413311157,
          "asymmetry_ratio": 0.12444168387698257
        },
        {
          "brand": "TotalEnergies",
          "avg_increase_cents": 19.88888888888889,
          "avg_decrease_cents": 0.6860902255639091,
          "avg_increase_speed_min": 167.8115740745432,
          "avg_decrease_speed_min": 40.50328947367021,
          "asymmetry_ratio": 0.241361715942658
        }
      ]
    },
    "Hamburg": {
      "lat": 53.55,
      "lng": 9.99,
      "leader_follower": [
        {
          "leader_brand": "ARAL",
          "follower_brand": "JET",
          "median_lag_minutes": 1.525,
          "event_count": 8
        },
        {
          "leader_brand": "ARAL",
          "follower_brand": "ESSO",
          "median_lag_minutes": 2.033333333333333,
          "event_count": 9
        },
        {
          "leader_brand": "ARAL",
          "follower_brand": "TotalEnergies",
          "median_lag_minutes": 4.05,
          "event_count": 9
        },
        {
          "leader_brand": "Shell",
          "follower_brand": "ESSO",
          "median_lag_minutes": 1.525,
          "event_count": 16
        },
        {
          "leader_brand": "Shell",
          "follower_brand": "JET",
          "median_lag_minutes": 2.025,
          "event_count": 14
        },
        {
          "leader_brand": "Shell",
          "follower_brand": "TotalEnergies",
          "median_lag_minutes": 4.058333333333334,
          "event_count": 16
        }
      ],
      "rockets_feathers": [
        {
          "brand": "ARAL",
          "avg_increase_cents": 18.359315589353614,
          "avg_decrease_cents": 0.8002265555465653,
          "avg_increase_speed_min": 348.0206907474411,
          "avg_decrease_speed_min": 43.21010734419237,
          "asymmetry_ratio": 0.1241595930730164
        },
        {
          "brand": "ESSO",
          "avg_increase_cents": 18.843601895734597,
          "avg_decrease_cents": 0.7238910234020257,
          "avg_increase_speed_min": 340.57590837307026,
          "avg_decrease_speed_min": 38.51847712189243,
          "asymmetry_ratio": 0.11309806764047123
        },
        {
          "brand": "JET",
          "avg_increase_cents": 17.243589743589745,
          "avg_decrease_cents": 0.7223353699932111,
          "avg_increase_speed_min": 357.5804131049663,
          "avg_decrease_speed_min": 41.48445915367305,
          "asymmetry_ratio": 0.11601434987294859
        },
        {
          "brand": "Shell",
          "avg_increase_cents": 19.28828828828829,
          "avg_decrease_cents": 0.7562315456980018,
          "avg_increase_speed_min": 295.5515615613678,
          "avg_decrease_speed_min": 40.55616974525299,
          "asymmetry_ratio": 0.13722197754936233
        },
        {
          "brand": "TotalEnergies",
          "avg_increase_cents": 15.96774193548387,
          "avg_decrease_cents": 0.6556263269639062,
          "avg_increase_speed_min": 391.242293907029,
          "avg_decrease_speed_min": 41.20945506015053,
          "asymmetry_ratio": 0.10532975524865709
        }
      ]
    },
    "Berlin": {
      "lat": 52.52,
      "lng": 13.41,
      "leader_follower": [
        {
          "leader_brand": "ARAL",
          "follower_brand": "JET",
          "median_lag_minutes": 1.525,
          "event_count": 8
        },
        {
          "leader_brand": "ARAL",
          "follower_brand": "ESSO",
          "median_lag_minutes": 2.033333333333333,
          "event_count": 9
        },
        {
          "leader_brand": "ARAL",
          "follower_brand": "TotalEnergies",
          "median_lag_minutes": 4.05,
          "event_count": 9
        },
        {
          "leader_brand": "Shell",
          "follower_brand": "JET",
          "median_lag_minutes": 2.0166666666666666,
          "event_count": 7
        },
        {
          "leader_brand": "Shell",
          "follower_brand": "ESSO",
          "median_lag_minutes": 2.033333333333333,
          "event_count": 9
        },
        {
          "leader_brand": "Shell",
          "follower_brand": "TotalEnergies",
          "median_lag_minutes": 4.05,
          "event_count": 9
        }
      ],
      "rockets_feathers": [
        {
          "brand": "ARAL",
          "avg_increase_cents": 23.055172413793102,
          "avg_decrease_cents": 0.9014506254990684,
          "avg_increase_speed_min": 244.54617816051788,
          "avg_decrease_speed_min": 43.85142179045505,
          "asymmetry_ratio": 0.1793175510666594
        },
        {
          "brand": "ESSO",
          "avg_increase_cents": 22.47747747747748,
          "avg_decrease_cents": 0.7273107486407361,
          "avg_increase_speed_min": 322.58768768803225,
          "avg_decrease_speed_min": 33.84055718201581,
          "asymmetry_ratio": 0.10490343702994114
        },
        {
          "brand": "JET",
          "avg_increase_cents": 21.675889328063242,
          "avg_decrease_cents": 0.712082912032356,
          "avg_increase_speed_min": 200.63754940667584,
          "avg_decrease_speed_min": 38.038131951479684,
          "asymmetry_ratio": 0.1895863065710572
        },
        {
          "brand": "Shell",
          "avg_increase_cents": 23.547619047619047,
          "avg_decrease_cents": 0.7513888021971162,
          "avg_increase_speed_min": 243.26782407387648,
          "avg_decrease_speed_min": 35.59963485426123,
          "asymmetry_ratio": 0.14633926615568446
        },
        {
          "brand": "TotalEnergies",
          "avg_increase_cents": 22.12962962962963,
          "avg_decrease_cents": 0.7422438515686104,
          "avg_increase_speed_min": 205.72394179929265,
          "avg_decrease_speed_min": 38.67610295181617,
          "asymmetry_ratio": 0.18800000920432078
        }
      ]
    },
    "M\u00fcnchen": {
      "lat": 48.14,
      "lng": 11.58,
      "leader_follower": [
        {
          "leader_brand": "ARAL",
          "follower_brand": "ESSO",
          "median_lag_minutes": 1.0333333333333334,
          "event_count": 9
        },
        {
          "leader_brand": "ARAL",
          "follower_brand": "JET",
          "median_lag_minutes": 1.525,
          "event_count": 8
        },
        {
          "leader_brand": "ARAL",
          "follower_brand": "TOTAL",
          "median_lag_minutes": 2.033333333333333,
          "event_count": 7
        },
        {
          "leader_brand": "ARAL",
          "follower_brand": "TotalEnergies",
          "median_lag_minutes": 4.05,
          "event_count": 9
        },
        {
          "leader_brand": "Shell",
          "follower_brand": "ESSO",
          "median_lag_minutes": 1.0333333333333334,
          "event_count": 9
        },
        {
          "leader_brand": "Shell",
          "follower_brand": "JET",
          "median_lag_minutes": 2.0166666666666666,
          "event_count": 7
        },
        {
          "leader_brand": "Shell",
          "follower_brand": "TOTAL",
          "median_lag_minutes": 2.033333333333333,
          "event_count": 6
        },
        {
          "leader_brand": "Shell",
          "follower_brand": "TotalEnergies",
          "median_lag_minutes": 4.05,
          "event_count": 9
        }
      ],
      "rockets_feathers": [
        {
          "brand": "ARAL",
          "avg_increase_cents": 21.09011627906977,
          "avg_decrease_cents": 0.8698550046772685,
          "avg_increase_speed_min": 374.726695735993,
          "avg_decrease_speed_min": 41.214250077973524,
          "asymmetry_ratio": 0.10998482506570678
        },
        {
          "brand": "ESSO",
          "avg_increase_cents": 22.653125,
          "avg_decrease_cents": 0.8363353346675562,
          "avg_increase_speed_min": 373.14807291695615,
          "avg_decrease_speed_min": 36.57479430730555,
          "asymmetry_ratio": 0.09801683825242546
        },
        {
          "brand": "JET",
          "avg_increase_cents": 21.179104477611943,
          "avg_decrease_cents": 0.7479674796747967,
          "avg_increase_speed_min": 408.7114427856712,
          "avg_decrease_speed_min": 33.67114258240816,
          "asymmetry_ratio": 0.08238365520895227
        },
        {
          "brand": "Shell",
          "avg_increase_cents": 22.10223642172524,
          "avg_decrease_cents": 0.7877101191138818,
          "avg_increase_speed_min": 394.9100106494329,
          "avg_decrease_speed_min": 34.925097406220274,
          "asymmetry_ratio": 0.08843811618952291
        },
        {
          "brand": "TOTAL",
          "avg_increase_cents": 22.777777777777768,
          "avg_decrease_cents": 0.7225501770956311,
          "avg_increase_speed_min": 381.9530864196519,
          "avg_decrease_speed_min": 31.52109405745828,
          "asymmetry_ratio": 0.08252608809351536
        },
        {
          "brand": "TotalEnergies",
          "avg_increase_cents": 23.01010101010101,
          "avg_decrease_cents": 0.7642330877427996,
          "avg_increase_speed_min": 251.471885522169,
          "avg_decrease_speed_min": 37.213033043085154,
          "asymmetry_ratio": 0.1479808884631939
        }
      ]
    },
    "K\u00f6ln": {
      "lat": 50.94,
      "lng": 6.96,
      "leader_follower": [
        {
          "leader_brand": "ARAL",
          "follower_brand": "JET",
          "median_lag_minutes": 1.525,
          "event_count": 8
        },
        {
          "leader_brand": "ARAL",
          "follower_brand": "ESSO",
          "median_lag_minutes": 2.033333333333333,
          "event_count": 9
        },
        {
          "leader_brand": "ARAL",
          "follower_brand": "TotalEnergies",
          "median_lag_minutes": 4.05,
          "event_count": 9
        },
        {
          "leader_brand": "Shell",
          "follower_brand": "JET",
          "median_lag_minutes": 2.025,
          "event_count": 8
        },
        {
          "leader_brand": "Shell",
          "follower_brand": "ESSO",
          "median_lag_minutes": 2.033333333333333,
          "event_count": 10
        },
        {
          "leader_brand": "Shell",
          "follower_brand": "TotalEnergies",
          "median_lag_minutes": 4.05,
          "event_count": 10
        }
      ],
      "rockets_feathers": [
        {
          "brand": "ARAL",
          "avg_increase_cents": 21.20877458396369,
          "avg_decrease_cents": 0.8744303485650943,
          "avg_increase_speed_min": 233.58585476511794,
          "avg_decrease_speed_min": 45.92306010594585,
          "asymmetry_ratio": 0.19660034702068643
        },
        {
          "brand": "ESSO",
          "avg_increase_cents": 23.42211055276382,
          "avg_decrease_cents": 0.8647402942740648,
          "avg_increase_speed_min": 330.96917922993254,
          "avg_decrease_speed_min": 37.586657212062825,
          "asymmetry_ratio": 0.11356543016940691
        },
        {
          "brand": "JET",
          "avg_increase_cents": 21.713541666666668,
          "avg_decrease_cents": 0.8245547555892383,
          "avg_increase_speed_min": 309.9612847217941,
          "avg_decrease_speed_min": 39.3281546040329,
          "asymmetry_ratio": 0.12688086074792182
        },
        {
          "brand": "Shell",
          "avg_increase_cents": 21.680257510729614,
          "avg_decrease_cents": 0.79613196814562,
          "avg_increase_speed_min": 328.15464949911626,
          "avg_decrease_speed_min": 38.06204778157799,
          "asymmetry_ratio": 0.115988141078222
        },
        {
          "brand": "TOTAL",
          "avg_increase_cents": 0.0,
          "avg_decrease_cents": 0.0,
          "avg_increase_speed_min": 0.0,
          "avg_decrease_speed_min": 9.395098039210817,
          "asymmetry_ratio": 0.0
        },
        {
          "brand": "TotalEnergies",
          "avg_increase_cents": 22.81132075471698,
          "avg_decrease_cents": 0.7928460342146187,
          "avg_increase_speed_min": 293.69103773630593,
          "avg_decrease_speed_min": 39.13521513736011,
          "asymmetry_ratio": 0.1332530111882343
        }
      ]
    }
  },
  "best_time": {
    "diesel": {
      "by_hour": [
        {
          "hour": 0,
          "avg_price": 1.8721
        },
        {
          "hour": 1,
          "avg_price": 1.8201
        },
        {
          "hour": 2,
          "avg_price": 1.8621
        },
        {
          "hour": 3,
          "avg_price": 1.855
        },
        {
          "hour": 4,
          "avg_price": 1.8596
        },
        {
          "hour": 5,
          "avg_price": 1.8552
        },
        {
          "hour": 6,
          "avg_price": 1.8489
        },
        {
          "hour": 7,
          "avg_price": 1.8446
        },
        {
          "hour": 8,
          "avg_price": 1.8407
        },
        {
          "hour": 9,
          "avg_price": 1.8389
        },
        {
          "hour": 10,
          "avg_price": 2.0557
        },
        {
          "hour": 11,
          "avg_price": 2.0067
        },
        {
          "hour": 12,
          "avg_price": 1.9601
        },
        {
          "hour": 13,
          "avg_price": 1.9296
        },
        {
          "hour": 14,
          "avg_price": 1.9089
        },
        {
          "hour": 15,
          "avg_price": 1.8888
        },
        {
          "hour": 16,
          "avg_price": 1.8757
        },
        {
          "hour": 17,
          "avg_price": 1.8653
        },
        {
          "hour": 18,
          "avg_price": 1.8569
        },
        {
          "hour": 19,
          "avg_price": 1.852
        },
        {
          "hour": 20,
          "avg_price": 1.8464
        },
        {
          "hour": 21,
          "avg_price": 1.855
        },
        {
          "hour": 22,
          "avg_price": 1.8541
        },
        {
          "hour": 23,
          "avg_price": 1.8632
        }
      ],
      "by_weekday": [
        {
          "day": "So",
          "dow": 0,
          "avg_price": 1.9246
        },
        {
          "day": "Mo",
          "dow": 1,
          "avg_price": 1.9016
        },
        {
          "day": "Di",
          "dow": 2,
          "avg_price": 1.9186
        },
        {
          "day": "Mi",
          "dow": 3,
          "avg_price": 1.9311
        },
        {
          "day": "Do",
          "dow": 4,
          "avg_price": 1.9478
        },
        {
          "day": "Fr",
          "dow": 5,
          "avg_price": 1.9293
        },
        {
          "day": "Sa",
          "dow": 6,
          "avg_price": 1.9249
        }
      ],
      "cheapest_hour": 1,
      "priciest_hour": 10,
      "hour_spread_cents": 23.6,
      "cheapest_day": "Mo",
      "priciest_day": "Do",
      "day_spread_cents": 4.6
    },
    "e5": {
      "by_hour": [
        {
          "hour": 0,
          "avg_price": 1.9446
        },
        {
          "hour": 1,
          "avg_price": 1.9246
        },
        {
          "hour": 2,
          "avg_price": 1.9371
        },
        {
          "hour": 3,
          "avg_price": 1.9415
        },
        {
          "hour": 4,
          "avg_price": 1.9344
        },
        {
          "hour": 5,
          "avg_price": 1.9308
        },
        {
          "hour": 6,
          "avg_price": 1.9247
        },
        {
          "hour": 7,
          "avg_price": 1.9197
        },
        {
          "hour": 8,
          "avg_price": 1.9169
        },
        {
          "hour": 9,
          "avg_price": 1.9145
        },
        {
          "hour": 10,
          "avg_price": 2.0969
        },
        {
          "hour": 11,
          "avg_price": 2.0614
        },
        {
          "hour": 12,
          "avg_price": 2.0268
        },
        {
          "hour": 13,
          "avg_price": 2.001
        },
        {
          "hour": 14,
          "avg_price": 1.9853
        },
        {
          "hour": 15,
          "avg_price": 1.9688
        },
        {
          "hour": 16,
          "avg_price": 1.9574
        },
        {
          "hour": 17,
          "avg_price": 1.9481
        },
        {
          "hour": 18,
          "avg_price": 1.9395
        },
        {
          "hour": 19,
          "avg_price": 1.9321
        },
        {
          "hour": 20,
          "avg_price": 1.927
        },
        {
          "hour": 21,
          "avg_price": 1.9292
        },
        {
          "hour": 22,
          "avg_price": 1.9364
        },
        {
          "hour": 23,
          "avg_price": 1.9291
        }
      ],
      "by_weekday": [
        {
          "day": "So",
          "dow": 0,
          "avg_price": 1.9887
        },
        {
          "day": "Mo",
          "dow": 1,
          "avg_price": 1.97
        },
        {
          "day": "Di",
          "dow": 2,
          "avg_price": 1.9946
        },
        {
          "day": "Mi",
          "dow": 3,
          "avg_price": 2.005
        },
        {
          "day": "Do",
          "dow": 4,
          "avg_price": 2.0091
        },
        {
          "day": "Fr",
          "dow": 5,
          "avg_price": 1.9943
        },
        {
          "day": "Sa",
          "dow": 6,
          "avg_price": 1.9896
        }
      ],
      "cheapest_hour": 9,
      "priciest_hour": 10,
      "hour_spread_cents": 18.2,
      "cheapest_day": "Mo",
      "priciest_day": "Do",
      "day_spread_cents": 3.9
    }
  },
  "brand_ranking": {
    "diesel": [
      {
        "brand": "ED",
        "is_oligopol": false,
        "avg_price": 1.8164,
        "station_count": 99
      },
      {
        "brand": "Globus SB Warenhaus",
        "is_oligopol": false,
        "avg_price": 1.8405,
        "station_count": 51
      },
      {
        "brand": "BayWa",
        "is_oligopol": false,
        "avg_price": 1.8673,
        "station_count": 79
      },
      {
        "brand": "Freie Tankstelle",
        "is_oligopol": false,
        "avg_price": 1.8815,
        "station_count": 162
      },
      {
        "brand": "freie Tankstelle",
        "is_oligopol": false,
        "avg_price": 1.8817,
        "station_count": 71
      },
      {
        "brand": "AVIA XPress",
        "is_oligopol": false,
        "avg_price": 1.884,
        "station_count": 208
      },
      {
        "brand": "Raiffeisen",
        "is_oligopol": false,
        "avg_price": 1.8866,
        "station_count": 434
      },
      {
        "brand": "SCORE",
        "is_oligopol": false,
        "avg_price": 1.8873,
        "station_count": 53
      },
      {
        "brand": "Supermarkt-Tankstelle",
        "is_oligopol": false,
        "avg_price": 1.8909,
        "station_count": 118
      },
      {
        "brand": "BFT",
        "is_oligopol": false,
        "avg_price": 1.8946,
        "station_count": 191
      },
      {
        "brand": "JET",
        "is_oligopol": true,
        "avg_price": 1.8961,
        "station_count": 686
      },
      {
        "brand": "bft",
        "is_oligopol": false,
        "avg_price": 1.8969,
        "station_count": 189
      },
      {
        "brand": "AVIA",
        "is_oligopol": false,
        "avg_price": 1.9004,
        "station_count": 635
      },
      {
        "brand": "Esso",
        "is_oligopol": true,
        "avg_price": 1.9004,
        "station_count": 83
      },
      {
        "brand": "Access",
        "is_oligopol": false,
        "avg_price": 1.9006,
        "station_count": 63
      },
      {
        "brand": "SB",
        "is_oligopol": false,
        "avg_price": 1.902,
        "station_count": 189
      },
      {
        "brand": "OIL!",
        "is_oligopol": false,
        "avg_price": 1.9021,
        "station_count": 196
      },
      {
        "brand": "ELAN",
        "is_oligopol": false,
        "avg_price": 1.9023,
        "station_count": 76
      },
      {
        "brand": "STAR",
        "is_oligopol": false,
        "avg_price": 1.9027,
        "station_count": 482
      },
      {
        "brand": "Hoyer",
        "is_oligopol": false,
        "avg_price": 1.9034,
        "station_count": 134
      },
      {
        "brand": "HEM",
        "is_oligopol": false,
        "avg_price": 1.9038,
        "station_count": 395
      },
      {
        "brand": "bft - Walther",
        "is_oligopol": false,
        "avg_price": 1.9093,
        "station_count": 66
      },
      {
        "brand": "CLASSIC",
        "is_oligopol": false,
        "avg_price": 1.9097,
        "station_count": 174
      },
      {
        "brand": "Q1",
        "is_oligopol": false,
        "avg_price": 1.9098,
        "station_count": 112
      },
      {
        "brand": "ORLEN",
        "is_oligopol": false,
        "avg_price": 1.9104,
        "station_count": 91
      },
      {
        "brand": "Markant",
        "is_oligopol": false,
        "avg_price": 1.9152,
        "station_count": 60
      },
      {
        "brand": "Sprint",
        "is_oligopol": false,
        "avg_price": 1.9155,
        "station_count": 96
      },
      {
        "brand": "TotalEnergies Autohof",
        "is_oligopol": false,
        "avg_price": 1.9197,
        "station_count": 53
      },
      {
        "brand": "NORDOEL",
        "is_oligopol": false,
        "avg_price": 1.9215,
        "station_count": 68
      },
      {
        "brand": "TotalEnergies",
        "is_oligopol": true,
        "avg_price": 1.9228,
        "station_count": 746
      },
      {
        "brand": "ESSO",
        "is_oligopol": true,
        "avg_price": 1.9246,
        "station_count": 1075
      },
      {
        "brand": "Westfalen",
        "is_oligopol": false,
        "avg_price": 1.9278,
        "station_count": 152
      },
      {
        "brand": "Shell",
        "is_oligopol": true,
        "avg_price": 1.9298,
        "station_count": 1670
      },
      {
        "brand": "team",
        "is_oligopol": false,
        "avg_price": 1.9358,
        "station_count": 85
      },
      {
        "brand": "AGIP ENI",
        "is_oligopol": false,
        "avg_price": 1.9427,
        "station_count": 476
      },
      {
        "brand": "ARAL",
        "is_oligopol": true,
        "avg_price": 1.9453,
        "station_count": 2170
      }
    ],
    "e5": [
      {
        "brand": "ED",
        "is_oligopol": false,
        "avg_price": 1.8775,
        "station_count": 99
      },
      {
        "brand": "Globus SB Warenhaus",
        "is_oligopol": false,
        "avg_price": 1.9133,
        "station_count": 51
      },
      {
        "brand": "BayWa",
        "is_oligopol": false,
        "avg_price": 1.9376,
        "station_count": 79
      },
      {
        "brand": "AVIA XPress",
        "is_oligopol": false,
        "avg_price": 1.9536,
        "station_count": 208
      },
      {
        "brand": "freie Tankstelle",
        "is_oligopol": false,
        "avg_price": 1.9563,
        "station_count": 71
      },
      {
        "brand": "Supermarkt-Tankstelle",
        "is_oligopol": false,
        "avg_price": 1.9563,
        "station_count": 118
      },
      {
        "brand": "Freie Tankstelle",
        "is_oligopol": false,
        "avg_price": 1.9566,
        "station_count": 162
      },
      {
        "brand": "Access",
        "is_oligopol": false,
        "avg_price": 1.9637,
        "station_count": 63
      },
      {
        "brand": "Esso",
        "is_oligopol": true,
        "avg_price": 1.9646,
        "station_count": 83
      },
      {
        "brand": "Raiffeisen",
        "is_oligopol": false,
        "avg_price": 1.9647,
        "station_count": 434
      },
      {
        "brand": "JET",
        "is_oligopol": true,
        "avg_price": 1.9653,
        "station_count": 686
      },
      {
        "brand": "bft",
        "is_oligopol": false,
        "avg_price": 1.9655,
        "station_count": 189
      },
      {
        "brand": "ELAN",
        "is_oligopol": false,
        "avg_price": 1.9669,
        "station_count": 76
      },
      {
        "brand": "Hoyer",
        "is_oligopol": false,
        "avg_price": 1.9671,
        "station_count": 134
      },
      {
        "brand": "SB",
        "is_oligopol": false,
        "avg_price": 1.9682,
        "station_count": 189
      },
      {
        "brand": "OIL!",
        "is_oligopol": false,
        "avg_price": 1.9686,
        "station_count": 196
      },
      {
        "brand": "BFT",
        "is_oligopol": false,
        "avg_price": 1.9689,
        "station_count": 191
      },
      {
        "brand": "AVIA",
        "is_oligopol": false,
        "avg_price": 1.9698,
        "station_count": 635
      },
      {
        "brand": "STAR",
        "is_oligopol": false,
        "avg_price": 1.9724,
        "station_count": 482
      },
      {
        "brand": "HEM",
        "is_oligopol": false,
        "avg_price": 1.974,
        "station_count": 395
      },
      {
        "brand": "Markant",
        "is_oligopol": false,
        "avg_price": 1.9759,
        "station_count": 60
      },
      {
        "brand": "ORLEN",
        "is_oligopol": false,
        "avg_price": 1.979,
        "station_count": 91
      },
      {
        "brand": "Sprint",
        "is_oligopol": false,
        "avg_price": 1.9794,
        "station_count": 96
      },
      {
        "brand": "Q1",
        "is_oligopol": false,
        "avg_price": 1.9801,
        "station_count": 112
      },
      {
        "brand": "CLASSIC",
        "is_oligopol": false,
        "avg_price": 1.9821,
        "station_count": 174
      },
      {
        "brand": "bft - Walther",
        "is_oligopol": false,
        "avg_price": 1.9833,
        "station_count": 66
      },
      {
        "brand": "TotalEnergies Autohof",
        "is_oligopol": false,
        "avg_price": 1.9842,
        "station_count": 53
      },
      {
        "brand": "SCORE",
        "is_oligopol": false,
        "avg_price": 1.9858,
        "station_count": 53
      },
      {
        "brand": "Westfalen",
        "is_oligopol": false,
        "avg_price": 1.9869,
        "station_count": 152
      },
      {
        "brand": "TotalEnergies",
        "is_oligopol": true,
        "avg_price": 1.9882,
        "station_count": 746
      },
      {
        "brand": "NORDOEL",
        "is_oligopol": false,
        "avg_price": 1.9888,
        "station_count": 68
      },
      {
        "brand": "ESSO",
        "is_oligopol": true,
        "avg_price": 1.9924,
        "station_count": 1075
      },
      {
        "brand": "Shell",
        "is_oligopol": true,
        "avg_price": 1.9947,
        "station_count": 1670
      },
      {
        "brand": "team",
        "is_oligopol": false,
        "avg_price": 2.008,
        "station_count": 85
      },
      {
        "brand": "ARAL",
        "is_oligopol": true,
        "avg_price": 2.0087,
        "station_count": 2170
      },
      {
        "brand": "AGIP ENI",
        "is_oligopol": false,
        "avg_price": 2.009,
        "station_count": 476
      }
    ]
  },
  "consumer_impact": {
    "diesel": {
      "oligopol_avg": 1.9288,
      "independent_avg": 1.899,
      "premium_cents_per_liter": 2.98,
      "premium_per_tank_eur": 1.49,
      "premium_per_year_eur": 77.48,
      "tank_size_liters": 50,
      "tanks_per_year": 52
    },
    "e5": {
      "oligopol_avg": 1.9942,
      "independent_avg": 1.9694,
      "premium_cents_per_liter": 2.48,
      "premium_per_tank_eur": 1.24,
      "premium_per_year_eur": 64.48,
      "tank_size_liters": 50,
      "tanks_per_year": 52
    }
  },
  "brent_decoupling_diesel": [
    {
      "date": "2026-06-01",
      "retail_avg": 1.9072500358026125,
      "brent_eur": 0.5308,
      "spread": 1.3764500358026126,
      "spread_z_score": 0.0,
      "is_abnormal": false
    },
    {
      "date": "2026-06-02",
      "retail_avg": 1.9206204384486614,
      "brent_eur": 0.5318,
      "spread": 1.3888204384486613,
      "spread_z_score": 0.7071067811865475,
      "is_abnormal": false
    },
    {
      "date": "2026-06-03",
      "retail_avg": 1.9311294722331591,
      "brent_eur": 0.5507,
      "spread": 1.3804294722331591,
      "spread_z_score": -0.23286191906836043,
      "is_abnormal": false
    },
    {
      "date": "2026-06-04",
      "retail_avg": 1.9477835315370888,
      "brent_eur": 0.5349,
      "spread": 1.412883531537089,
      "spread_z_score": 1.4232396375749918,
      "is_abnormal": false
    },
    {
      "date": "2026-06-05",
      "retail_avg": 1.9293287389034612,
      "brent_eur": 0.5257,
      "spread": 1.4036287389034614,
      "spread_z_score": 0.72352122076063,
      "is_abnormal": false
    },
    {
      "date": "2026-06-06",
      "retail_avg": 1.9248853528672938,
      "brent_eur": 0.5257,
      "spread": 1.3991853528672937,
      "spread_z_score": 0.39851754751595336,
      "is_abnormal": false
    },
    {
      "date": "2026-06-07",
      "retail_avg": 1.924556320375851,
      "brent_eur": 0.5257,
      "spread": 1.398856320375851,
      "spread_z_score": 0.3481032165072474,
      "is_abnormal": false
    },
    {
      "date": "2026-06-08",
      "retail_avg": 1.9010426739532313,
      "brent_eur": 0.5312,
      "spread": 1.3698426739532312,
      "spread_z_score": -1.4429870092406794,
      "is_abnormal": false
    },
    {
      "date": "2026-06-09",
      "retail_avg": 1.9169588231684842,
      "brent_eur": 0.5312,
      "spread": 1.385758823168484,
      "spread_z_score": -0.34926917389048673,
      "is_abnormal": false
    }
  ],
  "brent_decoupling_e5": [
    {
      "date": "2026-06-01",
      "retail_avg": 1.997602673869862,
      "brent_eur": 0.5308,
      "spread": 1.466802673869862,
      "spread_z_score": 0.0,
      "is_abnormal": false
    },
    {
      "date": "2026-06-02",
      "retail_avg": 2.0040738499439668,
      "brent_eur": 0.5318,
      "spread": 1.4722738499439667,
      "spread_z_score": 0.7071067811865476,
      "is_abnormal": false
    },
    {
      "date": "2026-06-03",
      "retail_avg": 2.00499153048619,
      "brent_eur": 0.5507,
      "spread": 1.45429153048619,
      "spread_z_score": -1.1026812832787662,
      "is_abnormal": false
    },
    {
      "date": "2026-06-04",
      "retail_avg": 2.009072861736597,
      "brent_eur": 0.5349,
      "spread": 1.474172861736597,
      "spread_z_score": 0.8135037358187387,
      "is_abnormal": false
    },
    {
      "date": "2026-06-05",
      "retail_avg": 1.9943253038341227,
      "brent_eur": 0.5257,
      "spread": 1.4686253038341226,
      "spread_z_score": 0.17853628932011903,
      "is_abnormal": false
    },
    {
      "date": "2026-06-06",
      "retail_avg": 1.9896106524699348,
      "brent_eur": 0.5257,
      "spread": 1.4639106524699348,
      "spread_z_score": -0.3897229198709954,
      "is_abnormal": false
    },
    {
      "date": "2026-06-07",
      "retail_avg": 1.9887012757425213,
      "brent_eur": 0.5257,
      "spread": 1.4630012757425215,
      "spread_z_score": -0.475318300969953,
      "is_abnormal": false
    },
    {
      "date": "2026-06-08",
      "retail_avg": 1.967313413771236,
      "brent_eur": 0.5312,
      "spread": 1.4361134137712361,
      "spread_z_score": -2.142528152329439,
      "is_abnormal": false
    },
    {
      "date": "2026-06-09",
      "retail_avg": 1.9865027869896474,
      "brent_eur": 0.5312,
      "spread": 1.4553027869896473,
      "spread_z_score": -0.5383218634507515,
      "is_abnormal": false
    }
  ],
  "spread_anomaly": {
    "diesel": {
      "period_days": 9,
      "abnormal_days": 0,
      "abnormal_pct": 0.0,
      "max_z_score": 1.42,
      "max_z_date": "2026-06-04",
      "threshold_z": 2.0,
      "mean_spread_cents": 139.1,
      "stddev_spread_cents": 1.4
    },
    "e5": {
      "period_days": 9,
      "abnormal_days": 0,
      "abnormal_pct": 0.0,
      "max_z_score": 0.81,
      "max_z_date": "2026-06-04",
      "threshold_z": 2.0,
      "mean_spread_cents": 146.2,
      "stddev_spread_cents": 1.2
    }
  },
  "price_breakdown": {
    "diesel": {
      "retail_avg_eur": 1.91,
      "energy_tax_eur": 0.33,
      "co2_eur": 0.15,
      "brent_eur": 0.53,
      "vat_eur": 0.3,
      "residual_eur": 0.6,
      "co2_price_eur_per_ton": 55.0,
      "co2_kg_per_liter": 2.64,
      "co2_price_source": "BEHG \u00a710, Mindestpreis Korridor 2026 (55\u201365 \u20ac/t); erste EEX-Auktion ab 1.7.2026",
      "energy_tax_source": "EnergieStG \u00a72 mit Tankrabatt 1.5.\u201330.6.2026 (-14,04 ct/L auf Diesel und Benzin)"
    },
    "e5": {
      "retail_avg_eur": 1.98,
      "energy_tax_eur": 0.51,
      "co2_eur": 0.13,
      "brent_eur": 0.53,
      "vat_eur": 0.32,
      "residual_eur": 0.49,
      "co2_price_eur_per_ton": 55.0,
      "co2_kg_per_liter": 2.32,
      "co2_price_source": "BEHG \u00a710, Mindestpreis Korridor 2026 (55\u201365 \u20ac/t); erste EEX-Auktion ab 1.7.2026",
      "energy_tax_source": "EnergieStG \u00a72 mit Tankrabatt 1.5.\u201330.6.2026 (-14,04 ct/L auf Diesel und Benzin)"
    },
    "constants": {
      "energy_tax_diesel_eur": 0.4704,
      "energy_tax_e5_eur": 0.6545,
      "co2_price_eur_per_ton": 55.0,
      "co2_price_source": "BEHG \u00a710, Mindestpreis Korridor 2026 (55\u201365 \u20ac/t); erste EEX-Auktion ab 1.7.2026",
      "co2_kg_per_liter_diesel": 2.64,
      "co2_kg_per_liter_e5": 2.32,
      "vat_rate": 0.19
    }
  }
}